mplot3d_dragger/__init__.py
mplot3d_dragger/dragger.py
mplot3d_dragger-0.0.0.dist-info/LICENSE
mplot3d_dragger-0.0.0.dist-info/METADATA
mplot3d_dragger-0.0.0.dist-info/WHEEL
mplot3d_dragger-0.0.0.dist-info/top_level.txt
mplot3d_dragger-0.0.0.dist-info/RECORD
