Metadata-Version: 2.1
Name: mplot3d-dragger
Version: 0.0.0
Summary: Allow dragging in matplotlib 3d plots.
Home-page: https://github.com/dashidhy/mplot3d_dragger
Author: Hongyuan Du
Author-email: du-hongyuan@outlook.com
License: MIT Licence
Keywords: matplotlib,mplot3d
Platform: UNKNOWN
Requires-Python: >=3.6.0
